{
  "package": {
    "dependencies": {
      "@testing-library/jest-dom": "^5.11.4",
      "@testing-library/react": "^11.1.0",
      "@testing-library/user-event": "^12.1.10",
      "@types/node": "^14.14.28",
      "@types/react": "^17.0.1",
      "@types/react-dom": "^17.0.1",
      "@types/jest": "^26.0.15",
      "@typescript-eslint/eslint-plugin": "^4.15.1",
      "eslint-config-react-app": "^6.0.0",
      "eslint-plugin-jest": "^24.1.5",
      "@typescript-eslint/parser": "^4.15.1",
      "eslint-plugin-react-app": "^6.2.2",
      "eslint-plugin-testing-library": "^3.10.1",
      "typescript": "^4.1.5",
      "web-vitals": "^1.0.1",
      "eslint": "^7.20.0",
      "eslint-plugin-import": "^2.22.1",
      "eslint-plugin-prettier": "^3.3.1",
      "prettier": "^2.2.1",
      "customize-cra": "^1.0.0",
      "react-app-rewired": "^2.1.8",
      "node-sass": "^5.0.0"
    },
    "eslintConfig": {
      "extends": ["react-app", "react-app/jest"],
      "plugins": ["prettier", "import"],
      "rules": {
        "prettier/prettier": "warn",
        "import/order": "warn",
        "@typescript-eslint/consistent-type-imports": "warn"
      }
    },
    "scripts": {
      "start": "react-app-rewired start",
      "build": "react-app-rewired build",
      "lint": "eslint src",
      "format": "prettier --check src",
      "test": "jest"
    }
  }
}
